tasks_collector/__init__.py
tasks_collector/__main__.py
tasks_collector/reportgenerator/__init__.py
tasks_collector/reportgenerator/api.py
tasks_collector/tasksconverter/__init__.py
tasks_collector/tasksconverter/api.py
tasks_collector/tasksdb/__init__.py
tasks_collector/tasksdb/api.py
tasks_collector/tasksscraper/__init__.py
tasks_collector/tasksscraper/jirascraper.py
tasks_collector/tasksscraper/outlookscraper.py
tasks_collector/tasksscraper/trelloscraper.py
tests/__init__.py
tests/test_jirascraper.py
tests/test_outlookscraper.py
tests/test_reportgenerator.py
tests/test_tasksconverter.py
tests/test_tasksdb.py
tests/test_trelloscraper.py
venv/__init__.py
venv/lib/__init__.py
tasks_collector-0.9.7.dist-info/LICENSE
tasks_collector-0.9.7.dist-info/METADATA
tasks_collector-0.9.7.dist-info/WHEEL
tasks_collector-0.9.7.dist-info/entry_points.txt
tasks_collector-0.9.7.dist-info/top_level.txt
tasks_collector-0.9.7.dist-info/RECORD
