Metadata-Version: 2.1
Name: tasks-collector
Version: 0.9.7
Summary: A small project for collecting tasks
Home-page: https://github.com/engdan77/tasks_collector
Author: Daniel Engvall
Author-email: daniel@engvalls.eu
License: MIT
Platform: UNKNOWN
Classifier: Programming Language :: Python :: 3
Classifier: License :: OSI Approved :: MIT License
Classifier: Environment :: MacOS X
Classifier: Topic :: Office/Business
Requires-Dist: shiboken2 (>=5.12.0)
Requires-Dist: loguru (==0.3.2)
Requires-Dist: jira (==2.0.0)
Requires-Dist: dateparser (==0.7.0)
Requires-Dist: peewee (==3.7.1)
Requires-Dist: numpy (==1.17.4)
Requires-Dist: keyring (==15.1.0)
Requires-Dist: matplotlib (==3.3.2)
Requires-Dist: PySimpleGUIQt (==0.22.0)
Requires-Dist: PySide2 (>=5.12.0)
Requires-Dist: Gooey (==1.0.2)
Requires-Dist: pandas (>=0.23.4)
Requires-Dist: dictdiffer (==0.7.1)
Requires-Dist: appdirs (==1.4.3)
Requires-Dist: scipy (==1.3.3)
Requires-Dist: py-trello (==0.15.0)
Requires-Dist: osascript (==2019.4.13)
Requires-Dist: tox (==3.14.1)
Requires-Dist: pytest-mock (==1.11.2)
Requires-Dist: commonmark (==0.9.1)
Requires-Dist: recommonmark (==0.6.0)
Requires-Dist: sphinx (==2.2.1)
Requires-Dist: sphinx-git (==11.0.0)
Requires-Dist: sphinx-rtd-theme (==0.4.3)
Requires-Dist: sphinxcontrib-applehelp (==1.0.1)
Requires-Dist: sphinxcontrib-devhelp (==1.0.1)
Requires-Dist: sphinxcontrib-htmlhelp (==1.0.2)
Requires-Dist: sphinxcontrib-jsmath (==1.0.1)
Requires-Dist: sphinxcontrib-qthelp (==1.0.2)
Requires-Dist: sphinxcontrib-serializinghtml (==1.1.3)
